[
    {
        "title": "中 배터리 CATL, 3분기 순이익 41% 증가...전기 트럭 성장 견인 - 엠투데이",
        "link": "https://www.autodaily.co.kr/news/articleView.html?idxno=537975",
        "ai_summary": "- CATL은 3분기 매출이 12.9% 늘고 순이익이 41.2% 급증하며 이익 성장이 매출을 크게 상회했다.\n- 1~9월 중국 배터리 시장 점유율 42.75%(210.67GWh 공급), 9월 32.51GWh 출하로 BEV·PHEV 전 영역에서 우위를 유지했다.\n- 션싱·기린 등 차세대 제품이 출하의 약 60%를 차지하고, 전기 트럭 등 상용차 수요와 고수익 제품 확대가 수익성·현금흐름을 뒷받침했다.",
        "image_final_width": 640,
        "image_final_height": 407,
        "image_cid": "news_image_0"
    },
    {
        "title": "콴티파이-마음인베, 패션·뷰티 풀필먼트 '아이아이씨에이' 투자 - 블로터",
        "link": "https://www.bloter.net/news/articleView.html?idxno=645972",
        "ai_summary": "- 콴티파이인큐베이터와 마음인베스트먼트가 공동 조합으로 패션·뷰티 풀필먼트사 ‘아이아이씨에이’에 투자해 AI 물류 플랫폼 ‘핑고’ 고도화·상용화를 추진한다.  \n- 핑고는 입고·재고·배송·반품 전 과정을 자동화하고 550여 이커머스 연동, 전담 MD·CS, AI 대시보드로 브랜드 운영 효율을 높인다.  \n- 아이아이씨에이는 투자금으로 1000평 규모 센터 확보, 파트너십 확대, 핵심 인력 채용을 계획하며, 투자사들은 후속 투자와 네트워크 지원을 예고했다.",
        "image_final_width": 640,
        "image_final_height": 358,
        "image_cid": "news_image_1"
    },
    {
        "title": "한국, IPEF 핵심광물 공급망 위기대응 모의훈련 주관 - 투데이에너지",
        "link": "https://www.todayenergy.kr/news/articleView.html?idxno=290065",
        "ai_summary": "- 한국이 IPEF 위기대응네트워크(CRN) 초대 의장국으로 서울에서 핵심광물 공급망 위기대응 모의훈련을 주관, 회원국 간 15일 내 긴급회의·공동대응 체계를 실전 점검했다.\n- 정제·가공국 가동 중단을 가정해 정보 공유→초기 대응→단계 격상→장관급 회의→공동선언까지 세분화된 절차로 실시간 훈련했다.\n- 한국·호주의 역량강화 사업 경과도 공유했으며, 한국은 TF 설치·로드맵 수립 등 CRN 리더십을 이어가며 인도태평양 공급망 회복력 제고가 기대된다.",
        "image_final_width": 640,
        "image_final_height": 358,
        "image_cid": "news_image_2"
    },
    {
        "title": "우성 베트남 법인, 펫푸드 자동화 설비 구축…글로벌 공급망 경쟁력 강화 속도 - 농수축산신문",
        "link": "https://www.aflnews.co.kr/news/articleView.html?idxno=306612",
        "ai_summary": "- 우성 베트남 법인이 정밀 중량·로봇 제어 포장 등 자동화 설비를 구축해 생산 효율과 품질을 끌어올렸다.\n- 토핑형 배합 등 현지 맞춤형 라인을 완비해 프리미엄·기능성 펫푸드 경쟁력을 강화하며 동남아 시장 공략을 가속한다.\n- 남부 컨터 하치장을 물류 허브로 운영, 리드타임 단축과 현지 대응력 제고로 태국·싱가포르 등 수출 확대 및 글로벌 공급망을 강화한다.",
        "image_final_width": 640,
        "image_final_height": 405,
        "image_cid": "news_image_3"
    },
    {
        "title": "콜롬비아 고위 공무원단, 부산진해경제자유구역청 방문 - 데일리한국",
        "link": "https://daily.hankooki.com/news/articleView.html?idxno=1285383",
        "ai_summary": "- 21일 콜롬비아 고위 공무원·교수 등 19명이 부산진해경제자유구역청(BJFEZ)을 방문해 스마트 물류·해양산업 노하우를 벤치마킹했다. \n- KOICA ‘까르따헤나 조선·기계 스마트산단 조성’ 역량강화의 일환으로, BJFEZ 인사이트 트립에서 항만 물류 인프라, 지구 개발, 스마트·그린 전환 사례를 살폈다. \n- BJFEZ 성공 모델의 콜롬비아 적용과 한-콜롬비아 경제협력 강화가 기대되며, BJFEZ는 중남미와의 교류 확대 의지를 밝혔다.",
        "image_final_width": 640,
        "image_final_height": 480,
        "image_cid": "news_image_4"
    },
    {
        "title": "美 하이-텍, 창고물류에 팩사이즈 스마트 패키징 통합 제공 - 로봇신문",
        "link": "https://www.irobotnews.com/news/articleView.html?idxno=42963",
        "ai_summary": "- 미국 하이-텍 인트라로지스틱스가 팩사이즈와 전략 제휴를 맺고, IntraOne 플랫폼과 팩사이즈의 온디맨드 스마트 패키징을 창고 작업 흐름에 통합한다.  \n- 이를 통해 처리량 향상, 자재 낭비 감소, 인력 효율 최적화, 투자 회수 기간 단축 등 측정 가능한 ROI를 제공하며, 픽투박스·AMR·ASRS·아웃바운드 분류와 연동된다.  \n- 팩사이즈는 패키지 부피 40% 축소, 골판지 20% 절감, 트럭 2,300만 대분 운송 회피, 디젤 약 20억 갤런 절감, 탄소 170억 kg 감축 효과를 제시했다.",
        "image_final_width": 640,
        "image_final_height": 426,
        "image_cid": "news_image_5"
    },
    {
        "title": "올비즈시스템, 조기 시행된 화물운송실적신고 소명 절차 대응 지원 - 필드뉴스",
        "link": "https://www.fieldnews.kr/news/articleView.html?idxno=22574",
        "ai_summary": "- 올비즈시스템이 예년보다 한 달 이상 앞당겨진 화물운송실적신고 소명 절차 대응을 위한 지원 서비스를 강화했다.\n- 소명은 10월부터 지자체별로 진행되며 직접운송 위반, 최소운송 기준 미달, 신고 불일치 등을 점검해 과태료·감차·사업정지 등 처분을 결정한다.\n- 법적 검토가 필요한 만큼 소명 항목을 정확히 이해하고 법령 근거 자료로 신속·정확히 대응하는 것이 처분 수위 조정의 핵심이다.",
        "image_final_width": 640,
        "image_final_height": 640,
        "image_cid": "news_image_6"
    },
    {
        "title": "쿠팡, ‘미래혁신기술박람회’서 AI·로보틱스 기반 물류 혁신 기술 공개 - 스마트경제",
        "link": "https://www.dailysmart.co.kr/news/articleView.html?idxno=114868",
        "ai_summary": "- 쿠팡이 대구 EXCO ‘FIX 2025’에서 로켓배송 핵심인 AI·로보틱스 물류 자동화 기술을 공개(AGV·ACR·소팅 봇·무인지게차·로보틱 배거 실물 전시).\n- 해당 기술로 물류 효율과 근무환경을 개선(예: 소팅 봇이 분류 업무량 약 65% 절감), 로봇 운영·유지보수 등 ‘오토메이션’ 채용도 확대.\n- 2027년까지 ‘전국민 100% 무료 로켓배송’ 목표로 인프라 확장에 수조 원 투자 중이며, 2026년까지 3조 원 이상 추가 투입 예정.",
        "image_final_width": 640,
        "image_final_height": 427,
        "image_cid": "news_image_7"
    },
    {
        "title": "'미래 먹거리' 전기차 배터리 재제조 시장, AI 기업과 손잡고 '친환경 물류' 생태계 속으로 - 스타트업엔",
        "link": "https://www.startupn.kr/news/articleView.html?idxno=54554",
        "ai_summary": "- 프리딕션(AI 배터리 데이터 분석)과 포엔(배터리 재제조)이 물류 시장용 재제조 배터리 순환 생태계·플랫폼 구축을 위한 MOU를 체결. \n- 전기차 배터리 재제조·진단 표준화와 데이터 통합(EView 연동, 내년 상반기 출시 예정)으로 유통·자원순환 고도화, 탄소 감축 및 ESG 경영 강화 추진. \n- 폐배터리 시장 성장 속 비용 절감·환경 효과 기대되나, 재제조 배터리 성능 신뢰 확보와 표준화 정착이 성패 관건.",
        "image_final_width": 640,
        "image_final_height": 480,
        "image_cid": "news_image_8"
    },
    {
        "title": "“지병인가, 과로사인가”…쿠팡, 배송기사 사망 두고 노조와 공방 - 스트레이트뉴스",
        "link": "https://www.straightnews.co.kr/news/articleView.html?idxno=284365",
        "ai_summary": "- 대구 쿠팡 택배기사가 뇌출혈로 사망하자, 쿠팡은 고혈압 등 지병에 의한 병사라 주장하고 노조는 장시간 노동에 따른 과로사라고 반박.\n- 노조는 분류·회수 등 ‘숨은 노동’으로 실제 주 62시간 근무·하루 520건 배송이라며 산업재해 과로사 기준(주 60시간) 초과를 주장, 쿠팡은 주 56시간 수준이라고 맞섬.\n- 2021년 사회적 합의 불이행과 ‘로켓배송’의 속도 경쟁 구조가 과로를 유발했다는 비판과 함께, 정부 특별근로감독 요구가 확산.",
        "image_final_width": 640,
        "image_final_height": 349,
        "image_cid": "news_image_9"
    }
]